{
  "movies": {
    "PRMovies": {
      "name": "PRMovies",
      "baseUrl": "https://prmovies.fitness",
      "url": "https://prmovies.fitness/?s=",
      "main": "div.movies-list div.ml-item",
      "title": "h2",
      "img": "a img[src]",
      "href": "a[href]"
    },
    "MkvCinemas": {
      "name": "MkvCinemas",
      "baseUrl": "https://mkvcinemas.bet",
      "url": "https://mkvcinemas.bet/?s=",
      "main": "div.movies-list div.ml-item",
      "title": "a span.mli-info h2",
      "img": "a img[src]",
      "href": "a[href]"
    },
    "FilmyHub": {
      "name": "FilmyHub",
      "baseUrl": "https://afilmyhub.mom",
      "url": "https://afilmyhub.mom/site-search.html?to-search=",
      "main": "div.container article.post",
      "title": "h3 a",
      "img": "img[src]",
      "href": "a[href]"
    }
  },
  "asian": {
    "Asianc": {
      "name": "Asianc",
      "baseUrl": "https://asianc.sh",
      "url": "https://asianc.sh/search?type=movies&keyword=",
      "main": "ul.switch-block li",
      "title": "a h3",
      "img": "a img[src]",
      "href": "a[href]"
    }
  },
  "anime": {
    "GoGoAnime": {
      "name": "GoGo Anime",
      "baseUrl": "https://ww9.gogoanimes.fi",
      "url": "https://ww9.gogoanimes.fi/search.html?keyword=",
      "main": "ul.items li",
      "title": "p.name a",
      "img": "div.img a img[src]",
      "href": "div.img a[href]"
    },
    "AnimeKai": {
      "name": "AnimeKai",
      "baseUrl": "https://animekai.to",
      "url": "https://animekai.to/browser?keyword=",
      "main": "div.aitem-wrapper div.aitem",
      "title": "a.title",
      "img": "a img[src]",
      "href": "a[href]"
    }
  },
  "novel": {
    "BestLightNovel": {
      "name": "Best Light Novel",
      "baseUrl": "https://bestlightnovel.com",
      "url": "https://bestlightnovel.com/search_novels/",
      "main": "div.update_item",
      "title": "h3 a",
      "img": "img[src]",
      "href": "h3 a[href]"
    },
    "稷下書院": {
      "name": "稷下書院",
      "baseUrl": "https://www.novel543.com",
      "url": "https://www.novel543.com/search/",
      "main": "ul.list li.media",
      "title": "div.media-content h3 a",
      "img": "div.media-left a img",
      "href": "div.media-content h3 a[href]"
    }
  }
}
